db_connector/__init__.py
db_connector/base_dao.py
db_connector/exceptions.py
db_connector/models/__init__.py
db_connector/mongo/__init__.py
db_connector/mongo/async_mongo_dao.py
db_connector/mongo/sync_mongo_dao.py
db_connector/mysql/__init__.py
db_connector/mysql/async_mysql_dao.py
db_connector/mysql/sync_mysql_dao.py
db_connector/utils/__init__.py
tests/__init__.py
tests/test_async_mongo_dao.py
tests/test_mysql_dao.py
cousin_db_connector-0.21.0.dist-info/METADATA
cousin_db_connector-0.21.0.dist-info/WHEEL
cousin_db_connector-0.21.0.dist-info/top_level.txt
cousin_db_connector-0.21.0.dist-info/RECORD
