Metadata-Version: 2.1
Name: cousin_db_connector
Version: 0.21.0
Summary: is a Python library designed to simplify connecting to and managing databases in asynchronous and synchronous applications. It provides a unified interface for interacting with different database engines, starting with support for MongoDB and expanding to others in the future.
Author: Eduardo Ponce
Requires-Python: >=3.9
Requires-Dist: PyJWT
Requires-Dist: fastapi
Requires-Dist: starlette
Requires-Dist: setuptools
Requires-Dist: motor
Requires-Dist: pymongo
Requires-Dist: twine
Requires-Dist: pytest
Requires-Dist: pytest-asyncio
Requires-Dist: pydantic
